mssh/__init__.py
mssh/config/__init__.py
mssh/config/msshconfig.py
mssh-0.1.1.data/data/completions/_mssh
mssh-0.1.1.data/data/completions/mssh
mssh-0.1.1.data/scripts/mssh
mssh-0.1.1.dist-info/DESCRIPTION.rst
mssh-0.1.1.dist-info/METADATA
mssh-0.1.1.dist-info/RECORD
mssh-0.1.1.dist-info/WHEEL
mssh-0.1.1.dist-info/metadata.json
mssh-0.1.1.dist-info/top_level.txt
