Metadata-Version: 2.0
Name: mssh
Version: 0.1.1
Summary: ssh manager
Home-page: https://github.com/foofilers/mssh
Author: Igor Maculan
Author-email: n3wtron@gmail.com
License: GPLv3
Keywords: ssh,manager
Platform: UNKNOWN
Requires-Dist: PyYAML
